{"cameraMode":{"drawMode":0,"name":"Shaded","section":"Shading Mode"},"sceneLighting":true,"audioPlay":false,"sceneViewState":{"m_AlwaysRefresh":false,"showFog":true,"showSkybox":true,"showFlares":true,"showImageEffects":true,"showParticleSystems":true,"showVisualEffectGraphs":true,"m_FxEnabled":true},"in2DMode":false,"pivot":{"x":1.052392840385437,"y":3.1559832096099855,"z":-6.047128677368164},"rotation":{"x":-0.2532520294189453,"y":0.0374542661011219,"z":-0.009756304323673249,"w":-0.9667167663574219},"size":0.8660253882408142,"orthographic":false}